tone/__init__.py
tone/analyzer.py
tone/main.py
tonneanalyzer_ankit-0.1.1.dist-info/METADATA
tonneanalyzer_ankit-0.1.1.dist-info/WHEEL
tonneanalyzer_ankit-0.1.1.dist-info/top_level.txt
tonneanalyzer_ankit-0.1.1.dist-info/RECORD
