Metadata-Version: 2.4
Name: tonneanalyzer-ankit
Version: 0.1.1
Summary: Hybrid rule + ML based tone analysis library
Author: Ankit Ghosh
License-Expression: MIT
Requires-Python: >=3.8
Requires-Dist: numpy
Requires-Dist: scikit-learn
Requires-Dist: joblib
